AUTHORS
LICENSE
MANIFEST.in
README.rst
setup.py
djangocms_accordion/__init__.py
djangocms_accordion/apps.py
djangocms_accordion/cms_plugins.py
djangocms_accordion/models.py
djangocms_accordion/views.py
djangocms_accordion/migrations/0001_initial.py
djangocms_accordion/migrations/0002_alter_cmsplugin_ptr.py
djangocms_accordion/migrations/__init__.py
djangocms_accordion/static/djangocms_accordion/css/accordion.css
djangocms_accordion/static/djangocms_accordion/css/accordion.less
djangocms_accordion/static/djangocms_accordion/js/accordion.js
djangocms_accordion/templates/djangocms_accordion/accordion_container.html
djangocms_accordion/templates/djangocms_accordion/accordion_tab.html
djangocms_simple_accordion.egg-info/PKG-INFO
djangocms_simple_accordion.egg-info/SOURCES.txt
djangocms_simple_accordion.egg-info/dependency_links.txt
djangocms_simple_accordion.egg-info/not-zip-safe
djangocms_simple_accordion.egg-info/requires.txt
djangocms_simple_accordion.egg-info/top_level.txt