Metadata-Version: 1.1
Name: djangocms-simple-accordion
Version: 0.1.0
Summary: Django-CMS Plugin for accordion tabs. It's easy to style and does not rely on big dependencies
Home-page: https://github.com/Blueshoe/djangocms-simple-accordion
Author: Maximilian Muth
Author-email: kontakt@maxi-muth.de
License: MIT
Keywords: django,Django CMS,accordion,tab,accordion-tab
Platform: UNKNOWN
Classifier: Development Status :: 4 - Beta
Classifier: Framework :: Django
Classifier: Environment :: Web Environment
Classifier: Intended Audience :: Developers
Classifier: Operating System :: OS Independent
Classifier: Programming Language :: Python
Classifier: Programming Language :: Python :: 2
Classifier: Programming Language :: Python :: 2.7
Classifier: Programming Language :: Python :: 3
Classifier: Programming Language :: Python :: 3.4
Classifier: Programming Language :: Python :: 3.5
Classifier: Programming Language :: Python :: 3.6
Classifier: Topic :: Internet :: WWW/HTTP
Classifier: Topic :: Internet :: WWW/HTTP :: Dynamic Content
Classifier: Topic :: Software Development :: Libraries :: Python Modules
Classifier: Topic :: Software Development :: Libraries :: Application Frameworks
